Workbook

Sheet 市场线
A1: 2026年党建品牌活动得分规则（市场线）
A2: 2026年党建品牌活动得分规则-区、县分公司
A3: 专项活动 | C3: 考核指标 | D3: 考核原则 | E3: 权重
A4: 联网业务“争3” 先锋工程 | B4: 强堡垒 | C4: 移宽增量收入 | D4: 考核移宽增量收入完成，以增幅3%为目标，线性得分，满分封顶。 | E4: 15
C5: 移宽存量收入 | D5: 考核移宽存量收保率，以94%为年度目标，完成目标得满分，每低1PP扣5分，扣完为止。 | E5: 15
B6: 树旗帜 | C6: 社区市场 | D6: 考核社区市场综合评价，综合得分大于70分得满分，每低10分扣1分，扣完为止。 | E6: 5
C7: 农村市场 | D7: 考核份额破局（不含解放），按照年度完成率排名，排名第一单位得满分，排名第二至第九依次扣0.25分。 | E7: 5
C8: 商户市场 | D8: 考核商户市场综合评价，综合得分大于70分得满分，每低10分扣1分，扣完为止。 | E8: 5
B9: 锻铁军 | C9: 营业员 | D9: 考核三支铁军队伍销售积分达标，达标率达到目标得满分，低于目标且最后得60%分，其他得（达标率/目标值*40%+60%）*分值。 | E9: 5
C10: 渠道经理 | E10: 5
C11: 智家工程师 | E11: 5
A12: 服务口碑“争3” 暖心工程 | B12: 优服务 | C12: TCSI综合满意度 | D12: TCSI综合满意度测评得分＞=84，本项不扣分；小于84分，每低1分扣2分，扣完为止（如本月无明细数据取上月，取固移网平均值）。 | E12: 10
C13: 服务工单综合评价 | D13: 评价率目标值96%，每低1个点扣2分，扣完为止。 | E13: 10
B14: 强合规 | C14: 工信部来量压降 | D14: 工信部来量压降分单位设置目标值（剔重），低于目标值得满分；每高于目标值1户扣2分，扣完为止。 | E14: 10
C15: 春雷服务工单投诉压降 | D15: 服务工单压降（本地投诉+10015）分单位设置目标值（2025年后四季度均值），低于目标值得满分；每高于目标值1个点扣2分，扣完为止。 | E15: 10
A16: 合计 | E16: =SUM(E4:E15) -> 100
B20: 2026年党建品牌活动得分规则-市场部/客服部
B21: 部门 | C21: 考核指标 | D21: 考核原则 | E21: 权重
B22: 市场部 | C22: 联网收入同比排名 | D22: 收入累计排名全省第3得满分，每低1名扣5分 | E22: 100
B23: 客服部 | C23: TCSI 综合满意度排名 | D23: TCSI 综合满意度排名全省第3得满分，每低1名扣5分 | E23: 100

Sheet 二季度考核结果
A1: 考核规则见市场线表 | B1: 单位 | C1: 移宽增量收入 | G1: 移宽存量收入 | L1: 社区市场 （解放7.5分） | N1: 商户市场 （解放7.5分） | P1: 农村市场（解放不考核） | T1: 铁军达标 | W1: 客户服务 | AA1: 合计 | AB1: 排名 | AG1: 铁军达标
C2: 目标 | D2: 完成值 | E2: 完成率 | F2: 得分 | G2: 拍照收入 | H2: 目标 | I2: 完成值 | J2: 完成率 | K2: 得分 | L2: 综合评价得分 | M2: 得分 | N2: 综合评价得分 | O2: 得分 | P2: 份额破局目标 | Q2: 完成值 | R2: 完成率 | S2: 得分 | T2: 营业员 | U2: 渠道经理 | V2: 智家工程师 | W2: TCSI综合满意度 | X2: 服务工单综合评价 | Y2: 工信部来量压降 | Z2: 春雷服务工单投诉压降 | AG2: 营业员 | AH2: 渠道经理 | AI2: 智家工程师
A3: 焦作市博爱县分公司 | B3: 博爱 | C3: 161.4 | D3: 134.86 | E3: =D3/C3 -> 0.83556382 | F3: =MIN(15,E3*15) -> 12.533457 | G3: 3671 | H3: 3550 | I3: 3528 | J3: =I3/H3 -> 0.99380282 | K3: =IF(J3<100%,MAX(15-(1-J3)*100*5,0),15) -> 11.901408 | L3: 78.8 | M3: 5 | N3: 42.2 | O3: 2.2 | P3: 57 | Q3: 19 | R3: 0.333 | S3: 3.5 | T3: =_xlfn.XLOOKUP($B3,Sheet5!$D:$D,Sheet5!I:I) -> 5 | U3: =_xlfn.XLOOKUP($B3,Sheet5!$D:$D,Sheet5!N:N) -> 4.0246154 | V3: =_xlfn.XLOOKUP($B3,Sheet5!$D:$D,Sheet5!S:S) -> 4.8697436 | W3: 10 | X3: 10 | Y3: 0 | Z3: 3.39 | AA3: =F3+K3+M3+O3+S3+T3+U3+V3+W3+X3+Y3+Z3 -> 72.419225 | AB3: =RANK(AA3,$AA$3:$AA$15) -> 10 | AC3: 博爱 | AF3: 武陟 | AG3: 0.421 | AH3: 0.2 | AI3: 0.405
A4: 焦作市孟州市分公司 | B4: 孟州 | C4: 158.57 | D4: 139.32 | E4: =D4/C4 -> 0.87860251 | F4: =MIN(15,E4*15) -> 13.179038 | G4: 3349 | H4: 3238 | I4: 3203 | J4: =I4/H4 -> 0.98919086 | K4: =IF(J4<100%,MAX(15-(1-J4)*100*5,0),15) -> 9.5954293 | L4: 67.37 | M4: 4 | N4: 46 | O4: 2.6 | P4: 72 | Q4: 57 | R4: 0.792 | S4: 4.75 | T4: =_xlfn.XLOOKUP($B4,Sheet5!$D:$D,Sheet5!I:I) -> 5 | U4: =_xlfn.XLOOKUP($B4,Sheet5!$D:$D,Sheet5!N:N) -> 3.9230769 | V4: =_xlfn.XLOOKUP($B4,Sheet5!$D:$D,Sheet5!S:S) -> 3.9887179 | W4: 10 | X4: 10 | Y4: 10 | Z4: 6.79 | AA4: =F4+K4+M4+O4+S4+T4+U4+V4+W4+X4+Y4+Z4 -> 83.826262 | AB4: =RANK(AA4,$AA$3:$AA$15) -> 4 | AC4: 孟州 | AF4: 沁阳 | AG4: 0.4 | AH4: 0.143 | AI4: 0.364
A5: 焦作市沁阳市分公司 | B5: 沁阳 | C5: 146.15 | D5: 117.84 | E5: =D5/C5 -> 0.8062949 | F5: =MIN(15,E5*15) -> 12.094424 | G5: 3497 | H5: 3382 | I5: 3378 | J5: =I5/H5 -> 0.99881727 | K5: =IF(J5<100%,MAX(15-(1-J5)*100*5,0),15) -> 14.408634 | L5: 60.24 | M5: 4 | N5: 40.3 | O5: 2 | P5: 95 | Q5: 66 | R5: 0.695 | S5: 4.25 | T5: =_xlfn.XLOOKUP($B5,Sheet5!$D:$D,Sheet5!I:I) -> 4.2605128 | U5: =_xlfn.XLOOKUP($B5,Sheet5!$D:$D,Sheet5!N:N) -> 3.7876923 | V5: =_xlfn.XLOOKUP($B5,Sheet5!$D:$D,Sheet5!S:S) -> 4.2276923 | W5: 10 | X5: 10 | Y5: 0 | Z5: 6.45 | AA5: =F5+K5+M5+O5+S5+T5+U5+V5+W5+X5+Y5+Z5 -> 75.478955 | AB5: =RANK(AA5,$AA$3:$AA$15) -> 8 | AC5: 沁阳 | AF5: 温县 | AG5: 0.4 | AH5: 0.5 | AI5: 0.417
A6: 焦作市温县分公司 | B6: 温县 | C6: 167.73 | D6: 150.84 | E6: =D6/C6 -> 0.89930245 | F6: =MIN(15,E6*15) -> 13.489537 | G6: 3841 | H6: 3714 | I6: 3700 | J6: =I6/H6 -> 0.99623048 | K6: =IF(J6<100%,MAX(15-(1-J6)*100*5,0),15) -> 13.11524 | L6: 86.21 | M6: 5 | N6: 49.7 | O6: 3 | P6: 63 | Q6: 48 | R6: 0.762 | S6: 4.5 | T6: =_xlfn.XLOOKUP($B6,Sheet5!$D:$D,Sheet5!I:I) -> 4.3784615 | U6: =_xlfn.XLOOKUP($B6,Sheet5!$D:$D,Sheet5!N:N) -> 4.5128205 | V6: =_xlfn.XLOOKUP($B6,Sheet5!$D:$D,Sheet5!S:S) -> 4.3128205 | W6: 10 | X6: 10 | Y6: 4 | Z6: 10 | AA6: =F6+K6+M6+O6+S6+T6+U6+V6+W6+X6+Y6+Z6 -> 86.308879 | AB6: =RANK(AA6,$AA$3:$AA$15) -> 3 | AC6: 温县 | AF6: 孟州 | AG6: 0.733 | AH6: 0.3 | AI6: 0.391
A7: 焦作市武陟县分公司 | B7: 武陟 | C7: 214.01 | D7: 191.69 | E7: =D7/C7 -> 0.89570581 | F7: =MIN(15,E7*15) -> 13.435587 | G7: 5361 | H7: 5184 | I7: 5159 | J7: =I7/H7 -> 0.99517747 | K7: =IF(J7<100%,MAX(15-(1-J7)*100*5,0),15) -> 12.588735 | L7: 47.04 | M7: 2 | N7: 40.7 | O7: 2.1 | P7: 95 | Q7: 32 | R7: 0.337 | S7: 3.75 | T7: =_xlfn.XLOOKUP($B7,Sheet5!$D:$D,Sheet5!I:I) -> 4.1835897 | U7: =_xlfn.XLOOKUP($B7,Sheet5!$D:$D,Sheet5!N:N) -> 3.4102564 | V7: =_xlfn.XLOOKUP($B7,Sheet5!$D:$D,Sheet5!S:S) -> 4.5138462 | W7: 10 | X7: 8 | Y7: 0 | Z7: 5.74 | AA7: =F7+K7+M7+O7+S7+T7+U7+V7+W7+X7+Y7+Z7 -> 69.722014 | AB7: =RANK(AA7,$AA$3:$AA$15) -> 11 | AC7: 武陟 | AF7: 博爱 | AG7: 0.667 | AH7: 0.333 | AI7: 0.64
A8: 焦作市修武县分公司 | B8: 修武 | C8: 129.71 | D8: 96.91 | E8: =D8/C8 -> 0.74712821 | F8: =MIN(15,E8*15) -> 11.206923 | G8: 2864 | H8: 2769 | I8: 2764 | J8: =I8/H8 -> 0.99819429 | K8: =IF(J8<100%,MAX(15-(1-J8)*100*5,0),15) -> 14.097147 | L8: 58.96 | M8: 3 | N8: 40.9 | O8: 2.1 | P8: 64 | Q8: 21 | R8: 0.328 | S8: 3.25 | T8: =_xlfn.XLOOKUP($B8,Sheet5!$D:$D,Sheet5!I:I) -> 5 | U8: =_xlfn.XLOOKUP($B8,Sheet5!$D:$D,Sheet5!N:N) -> 4.1733333 | V8: =_xlfn.XLOOKUP($B8,Sheet5!$D:$D,Sheet5!S:S) -> 3.7938462 | W8: 10 | X8: 10 | Y8: 10 | Z8: 10 | AA8: =F8+K8+M8+O8+S8+T8+U8+V8+W8+X8+Y8+Z8 -> 86.62125 | AB8: =RANK(AA8,$AA$3:$AA$15) -> 2 | AC8: 修武 | AF8: 修武 | AG8: 1 | AH8: 0.429 | AI8: 0.25
A9: 焦作市中站区分公司 | B9: 中站 | C9: 39.66 | D9: 39.53 | E9: =D9/C9 -> 0.99672214 | F9: =MIN(15,E9*15) -> 14.950832 | G9: 987 | H9: 954 | I9: 945 | J9: =I9/H9 -> 0.99056604 | K9: =IF(J9<100%,MAX(15-(1-J9)*100*5,0),15) -> 10.283019 | L9: 77.02 | M9: 5 | N9: 24.6 | O9: 0.5 | P9: 1 | Q9: 1 | R9: 1 | S9: 5 | T9: =_xlfn.XLOOKUP($B9,Sheet5!$D:$D,Sheet5!I:I) -> 3 | U9: =_xlfn.XLOOKUP($B9,Sheet5!$D:$D,Sheet5!N:N) -> 5 | V9: =_xlfn.XLOOKUP($B9,Sheet5!$D:$D,Sheet5!S:S) -> 3 | W9: 10 | X9: 6 | Y9: 2 | Z9: 1.74 | AA9: =F9+K9+M9+O9+S9+T9+U9+V9+W9+X9+Y9+Z9 -> 66.473851 | AB9: =RANK(AA9,$AA$3:$AA$15) -> 12 | AC9: 中站 | AF9: 解放 | AG9: 0.316 | AH9: 0.25 | AI9: 0.241
A10: 焦作市马村区分公司 | B10: 马村 | C10: 37.45 | D10: 31.38 | E10: =D10/C10 -> 0.83791722 | F10: =MIN(15,E10*15) -> 12.568758 | G10: 1021 | H10: 987 | I10: 992 | J10: =I10/H10 -> 1.0050659 | K10: =IF(J10<100%,MAX(15-(1-J10)*100*5,0),15) -> 15 | L10: 56.77 | M10: 3 | N10: 41.4 | O10: 2.1 | P10: 12 | Q10: 6 | R10: 0.5 | S10: 4 | T10: =_xlfn.XLOOKUP($B10,Sheet5!$D:$D,Sheet5!I:I) -> 4.8461538 | U10: =_xlfn.XLOOKUP($B10,Sheet5!$D:$D,Sheet5!N:N) -> 3.5128205 | V10: =_xlfn.XLOOKUP($B10,Sheet5!$D:$D,Sheet5!S:S) -> 3.6410256 | W10: 10 | X10: 10 | Y10: 10 | Z10: 10 | AA10: =F10+K10+M10+O10+S10+T10+U10+V10+W10+X10+Y10+Z10 -> 88.668758 | AB10: =RANK(AA10,$AA$3:$AA$15) -> 1 | AC10: 马村 | AF10: 山阳 | AG10: 0.375 | AH10: 0.25 | AI10: 0.05
A11: 焦作市解放区分公司 | B11: 解放 | C11: 163.11 | D11: 152.61 | E11: =D11/C11 -> 0.93562626 | F11: =MIN(15,E11*15) -> 14.034394 | G11: 4088 | H11: 3953 | I11: 3934 | J11: =I11/H11 -> 0.99519352 | K11: =IF(J11<100%,MAX(15-(1-J11)*100*5,0),15) -> 12.596762 | L11: 52.79 | M11: 5.5 | N11: 26.9 | O11: 0.7 | T11: =_xlfn.XLOOKUP($B11,Sheet5!$D:$D,Sheet5!I:I) -> 4.0584615 | U11: =_xlfn.XLOOKUP($B11,Sheet5!$D:$D,Sheet5!N:N) -> 3.6410256 | V11: =_xlfn.XLOOKUP($B11,Sheet5!$D:$D,Sheet5!S:S) -> 3.76 | W11: 10 | X11: 10 | Y11: 0 | Z11: 9.94 | AA11: =F11+K11+M11+O11+S11+T11+U11+V11+W11+X11+Y11+Z11 -> 74.230643 | AB11: =RANK(AA11,$AA$3:$AA$15) -> 9 | AC11: 解放 | AF11: 马村 | AG11: 0.6 | AH11: 0 | AI11: 0.125
A12: 焦作市山阳区分公司 | B12: 山阳 | C12: 133.63 | D12: 131.43 | E12: =D12/C12 -> 0.98353663 | F12: =MIN(15,E12*15) -> 14.753049 | G12: 3130 | H12: 3027 | I12: 2995 | J12: =I12/H12 -> 0.98942848 | K12: =IF(J12<100%,MAX(15-(1-J12)*100*5,0),15) -> 9.7142385 | L12: 44.12 | M12: 2 | N12: 28.9 | O12: 0.9 | P12: 1 | Q12: 0 | R12: 0 | S12: 3 | T12: =_xlfn.XLOOKUP($B12,Sheet5!$D:$D,Sheet5!I:I) -> 4.3035897 | U12: =_xlfn.XLOOKUP($B12,Sheet5!$D:$D,Sheet5!N:N) -> 3 | V12: =_xlfn.XLOOKUP($B12,Sheet5!$D:$D,Sheet5!S:S) -> 3.4615385 | W12: 10 | X12: 10 | Y12: 10 | Z12: 8.75 | AA12: =F12+K12+M12+O12+S12+T12+U12+V12+W12+X12+Y12+Z12 -> 79.882416 | AB12: =RANK(AA12,$AA$3:$AA$15) -> 6 | AC12: 山阳 | AF12: 中站 | AG12: 0 | AH12: 1 | AI12: 0
A13: 焦作市分公司 | B13: 合计 | C13: 1406.83 | D13: 1230.76 | E13: =D13/C13 -> 0.87484629 | F13: =MIN(15,E13*15) -> 13.122694 | G13: 34066 | H13: 32942 | I13: 32786 | J13: =I13/H13 -> 0.9952644 | K13: =IF(J13<100%,MAX(15-(1-J13)*100*5,0),15) -> 12.632202 | L13: =SUM(L3:L12)/10 -> 62.932 | M13: 4 | N13: =SUM(N3:N12)/10 -> 38.16 | O13: =SUM(O3:O12)/10 -> 1.82 | P13: 460 | Q13: 250 | R13: 0.543 | S13: =SUM(S3:S12)/9 -> 4 | T13: =_xlfn.XLOOKUP($B13,Sheet5!$D:$D,Sheet5!I:I) -> 4.5692308 | U13: =_xlfn.XLOOKUP($B13,Sheet5!$D:$D,Sheet5!N:N) -> 3.8933333 | V13: =_xlfn.XLOOKUP($B13,Sheet5!$D:$D,Sheet5!S:S) -> 4.1005128 | W13: 10 | X13: =SUM(X3:X12)/10 -> 9.4 | Y13: =SUM(Y3:Y12)/10 -> 4.6 | Z13: 7.28
Z14: 市场部 | AA14: =(F13+K13+M13+O13+S13+T13+U13+V13)/6*10 -> 80.229955 | AB14: =RANK(AA14,$AA$3:$AA$15) -> 5
Z15: 客服部 | AA15: =SUM(W13:Z13)/4*10 -> 78.2 | AB15: =RANK(AA15,$AA$3:$AA$15) -> 7

Sheet 政企线
A1: 2026年党建品牌活动得分规则（政企线）
A2: 专项活动 | B2: 指标 | C2: 分值 | D2: 评价规则 | E2: 应用部门
A3: 大企业市场 “党旗领航・提质争先” | B3: 大企业市场收入同比增幅 | C3: 15 | D3: 同比增幅为正开始得分，同比增幅每超1个百分点，得2分，36分封顶。 | E3: 六县、中站、马村、企业中心、政企部
B4: TOP321客户联网收入同比增幅 | C4: 15
B5: TOP321客户专线业务渗透率 | C5: 10 | D5: 按照渗透率线性计分
B6: 大企业标杆客户拓展完成率 | C6: 10 | D6: 按照目标完成率线性计分，1.2倍封顶
A7: “党建引领・份额争先” 公开市场份额攻坚 | B7: 公开市场运营商中标份额 | C7: 50 | D7: 目标为50%， 1.中标份额≥30%开始计分，按照目标完成率线性得分，最高得满分 2.有自研项目拓展给予1.1系数，最高得满分
A8: 合计 | C8: =SUM(C3:C7) -> 100
A10: 2026年党建品牌活动得分规则-政企部/政要中心/校园中心/创新中心
A11: 部门 | B11: 考核指标 | C11: 考核原则 | D11: 权重
A12: 政要中心/校园中心/创新中心/解放/山阳 | B12: 公开市场运营商中标份额 | C12: 目标为50%， 1.中标份额≥30%开始计分，按照目标完成率线性得分，最高得满分 2.有自研项目拓展给予1.1系数，最高得满分 | D12: 100

Sheet 网络线
A1: 2026年党建品牌活动得分规则（网络线）
A2: 2026年党建品牌活动得分规则-区、县分公司
A3: 专项活动 | B3: 考核指标 | C3: 考核原则 | D3: 权重
A4: 创标杆 | B4: 工匠行动 | C4: 根据各单位的工匠行动得分排名得分，第一名得30分，最后一名得15分，县分按30-2.14*（名次-1），区分按30-0.47*（名次-1) | D4: 10
B5: 固、移网TCSI满意度 | C5: 行业排名第一，得2分；行业排名第二，得1分。满意度70-81（不含81），1-2分线性积分。满意度的得分81分至84分之间，4-6分线性计分。等于84分积6分，高于84分，积8分，固移各占得分50% | D5: 10
B6: 移网重点场景达标率 | C6: 重点场景达标率大于等于98%得满分，低于94%不得分，中间线性得分 | D6: 10
B7: 宽带故障率 | C7: 按月评价，每月总分10分。 一、PON口（6分）： PON口超时工单占比≤1%，不扣分，＞1%，每超1单扣0.1分，扣完为止。 二、一二级（共4分）： ①工单量占一级分光器比（1分）：占比≤4%，得满分；4%＜占比≤6%（0.9-0分），线性得分；占比＞6%，0分； ②一二级间超时工单占比（3分）：占比≤6%，不扣分;占比>6%，每超1单扣0.005分，扣完为止。 | D7: 10
A8: 护安全 | B8: 网络安全 | C8: S级故障发生1例扣10分，锚点机房基础信息错误（以智慧运维数据系统为准），立行立改的隐患未整改，加扣5分 | D8: 20
B9: 网信安 | C9: 1、每发生1次钓鱼邮件信息事件，扣2分，扣完为止。 2、每发生1次终端中毒情况，扣1分，扣完为止。 3、未及时完成网信安相关工作，1次2分，如果被省公司通报，1次扣5分，扣完为止。 4、未及时完成资产备案，1次扣2分。 5、未及时完成漏洞扫描，”两高一弱“风险排查，1次扣2分。 6、发生网信安安全事件，1次扣10分。 | D9: 10
A10: 提质效 | B10: 绿网行动-移网 | C10: 根据各单位的基站配套焕新、天馈焕新、铁塔改自建整体进度进行排名评价，第一名得10分，最后一名得4分，中间线性得分，未达序时进度不得分 | D10: 10
B11: 绿网行动-线路 | C11: 根据各单位光缆网维护成本压降序时目标及进度，第一名得10分，最后一名得4分，中间线性得分，未达序时进度不得分 | D11: 10
B12: 绿网行动-动力 | C12: 根据各单位自有能耗压降序时目标及进度，第一名得10分，最后一名得4分，中间线性得分，未达序时进度不得分 | D12: 10
A13: 合计 | D13: =SUM(D4:D12) -> 100
A17: 2026年党建品牌活动得分规则-网络部/网络运营中心/交付中心
A18: 部门 | B18: 考核指标 | C18: 考核原则 | D18: 权重
A19: 网络部 | B19: 工匠行动总体排名 | C19: 工匠行动整体累计排名全省第1得满分，每低1名扣5分 | D19: 100
A20: 网络运营中心 | B20: 专业线工匠行动总体排名 | C20: 专业线累计排名全省第1得满分，每低1名扣5分 | D20: 100
A21: 交付中心 | B21: 专业线工匠行动总体排名 | C21: 专业线累计排名全省第1得满分，每低1名扣5分 | D21: 100

Sheet 职能线
A1: 2026年党建品牌活动得分规则（职能线）
A2: 党建重点工作
A3: 专项活动 | B3: 考核指标 | C3: 考核原则 | D3: 权重
A4: 落实基本培训制度 | B4: 研讨交流落实情况 | C4: 1.未按要求开展研讨交流1次扣0.5分 2.未按要求录入1次扣0.5分 | D4: 20
A5: “五星”支部建设、“四强”支部建设 | B5: 执行省公司对地市的考核指标 | C5: 按照省公司文件要求执行 | D5: 20
A6: “立足岗位做贡献 服务发展当先锋”主题实践活动 | B6: 1.深化“党员亮身份”活动情况 2.创建“党员先锋岗”情况 3.组建“党员先锋队”情况 | C6: 按照季度评分细则，每季度分数占5分 | D6: 20
A7: 党建信息 | B7: 1.党建信息数量 2.党建信息质量 | C7: 按照年度排名，1-10名满分；11-23名9.5分；24-28名9分。 | D7: 20
A8: 基层党支部两个清单落实情况 | B8: 1.党支部支委会年度议事决策清单落实情况 2.党支部支委会研究讨论党的建设事项清单落实情况 | C8: 未严格落实事项清单内容，1项扣0.1分 | D8: 20
A9: 合计 | D9: 100
A12: 提质增效
A13: 指标说明
A14: 执行省公司对地市的考核指标

Sheet Sheet5
E1: 铁军达标
E2: 营业员 | J2: 渠道经理 | O2: 智家工程师
E3: 202604 | F3: 202605 | G3: 202606 | H3: 月均 | J3: 202604 | K3: 202605 | L3: 202606 | M3: 月均 | O3: 202604 | P3: 202605 | Q3: 202606 | R3: 月均
D4: 武陟 | E4: 0.4 | F4: 0.333 | G4: 0.421 | H4: =AVERAGEA(E4:G4) -> 0.38466667 | I4: =_xlfn.IFS(H4>0.65,5,H4=MIN(H$4:H$13),3,TRUE,(H4/0.65*0.4+0.6)*5) -> 4.1835897 | J4: 0.1 | K4: 0.1 | L4: 0.2 | M4: =AVERAGEA(J4:L4) -> 0.13333333 | N4: =_xlfn.IFS(M4>0.65,5,M4=MIN(M$4:M$13),3,TRUE,(M4/0.65*0.4+0.6)*5) -> 3.4102564 | O4: 0.528 | P4: 0.543 | Q4: 0.405 | R4: =AVERAGEA(O4:Q4) -> 0.492 | S4: =_xlfn.IFS(R4>0.65,5,R4=MIN(R$4:R$13),3,TRUE,(R4/0.65*0.4+0.6)*5) -> 4.5138462
D5: 沁阳 | E5: 0.4 | F5: 0.429 | G5: 0.4 | H5: =AVERAGEA(E5:G5) -> 0.40966667 | I5: =_xlfn.IFS(H5>0.65,5,H5=MIN(H$4:H$13),3,TRUE,(H5/0.65*0.4+0.6)*5) -> 4.2605128 | J5: 0.375 | K5: 0.25 | L5: 0.143 | M5: =AVERAGEA(J5:L5) -> 0.256 | N5: =_xlfn.IFS(M5>0.65,5,M5=MIN(M$4:M$13),3,TRUE,(M5/0.65*0.4+0.6)*5) -> 3.7876923 | O5: 0.333 | P5: 0.5 | Q5: 0.364 | R5: =AVERAGEA(O5:Q5) -> 0.399 | S5: =_xlfn.IFS(R5>0.65,5,R5=MIN(R$4:R$13),3,TRUE,(R5/0.65*0.4+0.6)*5) -> 4.2276923
D6: 温县 | E6: 0.5 | F6: 0.444 | G6: 0.4 | H6: =AVERAGEA(E6:G6) -> 0.448 | I6: =_xlfn.IFS(H6>0.65,5,H6=MIN(H$4:H$13),3,TRUE,(H6/0.65*0.4+0.6)*5) -> 4.3784615 | J6: 0.308 | K6: 0.667 | L6: 0.5 | M6: =AVERAGEA(J6:L6) -> 0.49166667 | N6: =_xlfn.IFS(M6>0.65,5,M6=MIN(M$4:M$13),3,TRUE,(M6/0.65*0.4+0.6)*5) -> 4.5128205 | O6: 0.423 | P6: 0.44 | Q6: 0.417 | R6: =AVERAGEA(O6:Q6) -> 0.42666667 | S6: =_xlfn.IFS(R6>0.65,5,R6=MIN(R$4:R$13),3,TRUE,(R6/0.65*0.4+0.6)*5) -> 4.3128205
D7: 孟州 | E7: 0.667 | F7: 0.714 | G7: 0.733 | H7: =AVERAGEA(E7:G7) -> 0.70466667 | I7: =_xlfn.IFS(H7>0.65,5,H7=MIN(H$4:H$13),3,TRUE,(H7/0.65*0.4+0.6)*5) -> 5 | J7: 0.3 | K7: 0.3 | L7: 0.3 | M7: =AVERAGEA(J7:L7) -> 0.3 | N7: =_xlfn.IFS(M7>0.65,5,M7=MIN(M$4:M$13),3,TRUE,(M7/0.65*0.4+0.6)*5) -> 3.9230769 | O7: 0.24 | P7: 0.333 | Q7: 0.391 | R7: =AVERAGEA(O7:Q7) -> 0.32133333 | S7: =_xlfn.IFS(R7>0.65,5,R7=MIN(R$4:R$13),3,TRUE,(R7/0.65*0.4+0.6)*5) -> 3.9887179
D8: 博爱 | E8: 0.611 | F8: 0.722 | G8: 0.667 | H8: =AVERAGEA(E8:G8) -> 0.66666667 | I8: =_xlfn.IFS(H8>0.65,5,H8=MIN(H$4:H$13),3,TRUE,(H8/0.65*0.4+0.6)*5) -> 5 | J8: 0.333 | K8: 0.333 | L8: 0.333 | M8: =AVERAGEA(J8:L8) -> 0.333 | N8: =_xlfn.IFS(M8>0.65,5,M8=MIN(M$4:M$13),3,TRUE,(M8/0.65*0.4+0.6)*5) -> 4.0246154 | O8: 0.423 | P8: 0.76 | Q8: 0.64 | R8: =AVERAGEA(O8:Q8) -> 0.60766667 | S8: =_xlfn.IFS(R8>0.65,5,R8=MIN(R$4:R$13),3,TRUE,(R8/0.65*0.4+0.6)*5) -> 4.8697436
D9: 修武 | E9: 0.909 | F9: 0.8 | G9: 1 | H9: =AVERAGEA(E9:G9) -> 0.903 | I9: =_xlfn.IFS(H9>0.65,5,H9=MIN(H$4:H$13),3,TRUE,(H9/0.65*0.4+0.6)*5) -> 5 | J9: 0.429 | K9: 0.286 | L9: 0.429 | M9: =AVERAGEA(J9:L9) -> 0.38133333 | N9: =_xlfn.IFS(M9>0.65,5,M9=MIN(M$4:M$13),3,TRUE,(M9/0.65*0.4+0.6)*5) -> 4.1733333 | O9: 0.286 | P9: 0.238 | Q9: 0.25 | R9: =AVERAGEA(O9:Q9) -> 0.258 | S9: =_xlfn.IFS(R9>0.65,5,R9=MIN(R$4:R$13),3,TRUE,(R9/0.65*0.4+0.6)*5) -> 3.7938462
D10: 解放 | E10: 0.438 | F10: 0.278 | G10: 0.316 | H10: =AVERAGEA(E10:G10) -> 0.344 | I10: =_xlfn.IFS(H10>0.65,5,H10=MIN(H$4:H$13),3,TRUE,(H10/0.65*0.4+0.6)*5) -> 4.0584615 | J10: 0.25 | K10: 0.125 | L10: 0.25 | M10: =AVERAGEA(J10:L10) -> 0.20833333 | N10: =_xlfn.IFS(M10>0.65,5,M10=MIN(M$4:M$13),3,TRUE,(M10/0.65*0.4+0.6)*5) -> 3.6410256 | O10: 0.321 | P10: 0.179 | Q10: 0.241 | R10: =AVERAGEA(O10:Q10) -> 0.247 | S10: =_xlfn.IFS(R10>0.65,5,R10=MIN(R$4:R$13),3,TRUE,(R10/0.65*0.4+0.6)*5) -> 3.76
D11: 山阳 | E11: 0.467 | F11: 0.429 | G11: 0.375 | H11: =AVERAGEA(E11:G11) -> 0.42366667 | I11: =_xlfn.IFS(H11>0.65,5,H11=MIN(H$4:H$13),3,TRUE,(H11/0.65*0.4+0.6)*5) -> 4.3035897 | J11: 0 | K11: 0.125 | L11: 0.25 | M11: =AVERAGEA(J11:L11) -> 0.125 | N11: =_xlfn.IFS(M11>0.65,5,M11=MIN(M$4:M$13),3,TRUE,(M11/0.65*0.4+0.6)*5) -> 3 | O11: 0.2 | P11: 0.2 | Q11: 0.05 | R11: =AVERAGEA(O11:Q11) -> 0.15 | S11: =_xlfn.IFS(R11>0.65,5,R11=MIN(R$4:R$13),3,TRUE,(R11/0.65*0.4+0.6)*5) -> 3.4615385
D12: 马村 | E12: 0.6 | F12: 0.6 | G12: 0.6 | H12: =AVERAGEA(E12:G12) -> 0.6 | I12: =_xlfn.IFS(H12>0.65,5,H12=MIN(H$4:H$13),3,TRUE,(H12/0.65*0.4+0.6)*5) -> 4.8461538 | J12: 0 | K12: 0.5 | L12: 0 | M12: =AVERAGEA(J12:L12) -> 0.16666667 | N12: =_xlfn.IFS(M12>0.65,5,M12=MIN(M$4:M$13),3,TRUE,(M12/0.65*0.4+0.6)*5) -> 3.5128205 | O12: 0.25 | P12: 0.25 | Q12: 0.125 | R12: =AVERAGEA(O12:Q12) -> 0.20833333 | S12: =_xlfn.IFS(R12>0.65,5,R12=MIN(R$4:R$13),3,TRUE,(R12/0.65*0.4+0.6)*5) -> 3.6410256
D13: 中站 | E13: 0.667 | F13: 0.25 | G13: 0 | H13: =AVERAGEA(E13:G13) -> 0.30566667 | I13: =_xlfn.IFS(H13>0.65,5,H13=MIN(H$4:H$13),3,TRUE,(H13/0.65*0.4+0.6)*5) -> 3 | J13: 0 | K13: 1 | L13: 1 | M13: =AVERAGEA(J13:L13) -> 0.66666667 | N13: =_xlfn.IFS(M13>0.65,5,M13=MIN(M$4:M$13),3,TRUE,(M13/0.65*0.4+0.6)*5) -> 5 | O13: 0 | P13: 0 | Q13: 0 | R13: =AVERAGEA(O13:Q13) -> 0 | S13: =_xlfn.IFS(R13>0.65,5,R13=MIN(R$4:R$13),3,TRUE,(R13/0.65*0.4+0.6)*5) -> 3
D14: 合计 | E14: 0.537 | F14: 0.493 | G14: 0.5 | H14: =AVERAGEA(E14:G14) -> 0.51 | I14: =(H14/0.65*0.4+0.6)*5 -> 4.5692308 | J14: 0.253 | K14: 0.307 | L14: 0.311 | M14: =AVERAGEA(J14:L14) -> 0.29033333 | N14: =(M14/0.65*0.4+0.6)*5 -> 3.8933333 | O14: 0.344 | P14: 0.393 | Q14: 0.336 | R14: =AVERAGEA(O14:Q14) -> 0.35766667 | S14: =(R14/0.65*0.4+0.6)*5 -> 4.1005128
